datasette_explain/__init__.py
datasette_explain-0.2.1.dist-info/LICENSE
datasette_explain-0.2.1.dist-info/METADATA
datasette_explain-0.2.1.dist-info/WHEEL
datasette_explain-0.2.1.dist-info/entry_points.txt
datasette_explain-0.2.1.dist-info/top_level.txt
datasette_explain-0.2.1.dist-info/RECORD
