Metadata-Version: 2.1
Name: datasette-explain
Version: 0.2.1
Summary: Explain SQL queries executed using Datasette
Author: Simon Willison
License: Apache-2.0
Project-URL: Homepage, https://datasette.io/plugins/datasette-explain
Project-URL: Changelog, https://github.com/simonw/datasette-explain/releases
Project-URL: Issues, https://github.com/simonw/datasette-explain/issues
Project-URL: CI, https://github.com/simonw/datasette-explain/actions
Classifier: Framework :: Datasette
Classifier: License :: OSI Approved :: Apache Software License
Requires-Python: >=3.8
License-File: LICENSE
Requires-Dist: datasette
Provides-Extra: test
Requires-Dist: pytest ; extra == 'test'
Requires-Dist: pytest-asyncio ; extra == 'test'
